{
  "unversionedId": "why/host_centric",
  "id": "why/host_centric",
  "title": "The host-centric web",
  "description": "One major problem of the current host-centric internet architecture is that documents are host-certified - we refer to data by location instead of contents, but that leads to link rot & content drift. Information is fragile without an ecosystem of identity, reputation, references, context & liability - our digital history lacks a solid foundation. We can't expect everyone to be like @balajis - linking to articles from the Internet Archive (Example",
  "source": "@site/docs/why/host_centric.md",
  "sourceDirName": "why",
  "slug": "/why/host_centric",
  "permalink": "/docs/why/host_centric",
  "draft": false,
  "tags": [],
  "version": "current",
  "frontMatter": {}
}